orco_nmr/__init__.py
orco_nmr/cli.py
orco_nmr/core.py
orco_nmr/stats.py
orco_nmr/stats_refdb_bmrb1.csv
orco_nmr-0.1.152.dist-info/METADATA
orco_nmr-0.1.152.dist-info/WHEEL
orco_nmr-0.1.152.dist-info/entry_points.txt
orco_nmr-0.1.152.dist-info/top_level.txt
orco_nmr-0.1.152.dist-info/RECORD
