Metadata-Version: 2.4
Name: orco-nmr
Version: 0.1.152
Summary: OpenSource Residue Classification Oracle (ORCO)
Author-email: Owen Raymond <owen.raymond@ucf.edu>
Project-URL: Homepage, https://github.com/Raymond-Owen1-137/orco_package
Project-URL: Source, https://github.com/Raymond-Owen1-137/orco_package
Requires-Python: >=3.8
Requires-Dist: scipy
